[
  {
    "dataset": "Weather",
    "pred_len": 96,
    "variant": "DynamicOnly",
    "n": 1,
    "seeds": "2021",
    "mse_mean": 0.1785683035850525,
    "mse_std": 0.0,
    "mae_mean": 0.21640051901340485,
    "mae_std": 0.0,
    "mse_mean_trunc3": 0.178,
    "mse_std_trunc3": 0.0,
    "mae_mean_trunc3": 0.216,
    "mae_std_trunc3": 0.0,
    "duration_mean_seconds": 139.0,
    "peak_gpu_memory_max_mib": 217.888,
    "parameters_total": 198826
  },
  {
    "dataset": "Weather",
    "pred_len": 96,
    "variant": "FixedGate",
    "n": 1,
    "seeds": "2021",
    "mse_mean": 0.1500815600156784,
    "mse_std": 0.0,
    "mae_mean": 0.19137528538703918,
    "mae_std": 0.0,
    "mse_mean_trunc3": 0.15,
    "mse_std_trunc3": 0.0,
    "mae_mean_trunc3": 0.191,
    "mae_std_trunc3": 0.0,
    "duration_mean_seconds": 85.0,
    "peak_gpu_memory_max_mib": 219.637,
    "parameters_total": 198826
  },
  {
    "dataset": "Weather",
    "pred_len": 96,
    "variant": "Full",
    "n": 3,
    "seeds": "2021,2022,2023",
    "mse_mean": 0.1498058040936788,
    "mse_std": 0.00015852559161790881,
    "mae_mean": 0.19102411468823752,
    "mae_std": 0.00048615266521084263,
    "mse_mean_trunc3": 0.149,
    "mse_std_trunc3": 0.0,
    "mae_mean_trunc3": 0.191,
    "mae_std_trunc3": 0.0,
    "duration_mean_seconds": 88.66666666666667,
    "peak_gpu_memory_max_mib": 220.326,
    "parameters_total": 198826
  },
  {
    "dataset": "Weather",
    "pred_len": 96,
    "variant": "GlobalOnly",
    "n": 1,
    "seeds": "2021",
    "mse_mean": 0.16214412450790405,
    "mse_std": 0.0,
    "mae_mean": 0.20558381080627441,
    "mae_std": 0.0,
    "mse_mean_trunc3": 0.162,
    "mse_std_trunc3": 0.0,
    "mae_mean_trunc3": 0.205,
    "mae_std_trunc3": 0.0,
    "duration_mean_seconds": 107.0,
    "peak_gpu_memory_max_mib": 219.19,
    "parameters_total": 198826
  },
  {
    "dataset": "Weather",
    "pred_len": 96,
    "variant": "NoDynFilt",
    "n": 3,
    "seeds": "2021,2022,2023",
    "mse_mean": 0.17948387066523233,
    "mse_std": 0.00027955401380159404,
    "mae_mean": 0.21731271346410116,
    "mae_std": 0.000834386822739595,
    "mse_mean_trunc3": 0.179,
    "mse_std_trunc3": 0.0,
    "mae_mean_trunc3": 0.217,
    "mae_std_trunc3": 0.0,
    "duration_mean_seconds": 105.0,
    "peak_gpu_memory_max_mib": 211.558,
    "parameters_total": 198826
  },
  {
    "dataset": "Weather",
    "pred_len": 96,
    "variant": "NoSDE",
    "n": 3,
    "seeds": "2021,2022,2023",
    "mse_mean": 0.17948387066523233,
    "mse_std": 0.00027955401380159404,
    "mae_mean": 0.21731271346410116,
    "mae_std": 0.000834386822739595,
    "mse_mean_trunc3": 0.179,
    "mse_std_trunc3": 0.0,
    "mae_mean_trunc3": 0.217,
    "mae_std_trunc3": 0.0,
    "duration_mean_seconds": 104.66666666666667,
    "peak_gpu_memory_max_mib": 210.722,
    "parameters_total": 198826
  },
  {
    "dataset": "Weather",
    "pred_len": 96,
    "variant": "WrongPhase",
    "n": 1,
    "seeds": "2021",
    "mse_mean": 0.1614103764295578,
    "mse_std": 0.0,
    "mae_mean": 0.20484665036201477,
    "mae_std": 0.0,
    "mse_mean_trunc3": 0.161,
    "mse_std_trunc3": 0.0,
    "mae_mean_trunc3": 0.204,
    "mae_std_trunc3": 0.0,
    "duration_mean_seconds": 110.0,
    "peak_gpu_memory_max_mib": 218.441,
    "parameters_total": 75346
  },
  {
    "dataset": "Weather",
    "pred_len": 336,
    "variant": "DynamicOnly",
    "n": 1,
    "seeds": "2021",
    "mse_mean": 0.28174158930778503,
    "mse_std": 0.0,
    "mae_mean": 0.296685129404068,
    "mae_std": 0.0,
    "mse_mean_trunc3": 0.281,
    "mse_std_trunc3": 0.0,
    "mae_mean_trunc3": 0.296,
    "mae_std_trunc3": 0.0,
    "duration_mean_seconds": 192.0,
    "peak_gpu_memory_max_mib": 423.431,
    "parameters_total": 260506
  },
  {
    "dataset": "Weather",
    "pred_len": 336,
    "variant": "FixedGate",
    "n": 1,
    "seeds": "2021",
    "mse_mean": 0.25820595026016235,
    "mse_std": 0.0,
    "mae_mean": 0.28278687596321106,
    "mae_std": 0.0,
    "mse_mean_trunc3": 0.258,
    "mse_std_trunc3": 0.0,
    "mae_mean_trunc3": 0.282,
    "mae_std_trunc3": 0.0,
    "duration_mean_seconds": 158.0,
    "peak_gpu_memory_max_mib": 425.141,
    "parameters_total": 260506
  },
  {
    "dataset": "Weather",
    "pred_len": 336,
    "variant": "Full",
    "n": 3,
    "seeds": "2021,2022,2023",
    "mse_mean": 0.25826191902160645,
    "mse_std": 0.000325782963611289,
    "mae_mean": 0.28241289655367535,
    "mae_std": 0.00021778691058986358,
    "mse_mean_trunc3": 0.258,
    "mse_std_trunc3": 0.0,
    "mae_mean_trunc3": 0.282,
    "mae_std_trunc3": 0.0,
    "duration_mean_seconds": 151.66666666666666,
    "peak_gpu_memory_max_mib": 425.306,
    "parameters_total": 260506
  },
  {
    "dataset": "Weather",
    "pred_len": 336,
    "variant": "GlobalOnly",
    "n": 1,
    "seeds": "2021",
    "mse_mean": 0.2634716033935547,
    "mse_std": 0.0,
    "mae_mean": 0.28880730271339417,
    "mae_std": 0.0,
    "mse_mean_trunc3": 0.263,
    "mse_std_trunc3": 0.0,
    "mae_mean_trunc3": 0.288,
    "mae_std_trunc3": 0.0,
    "duration_mean_seconds": 229.0,
    "peak_gpu_memory_max_mib": 423.444,
    "parameters_total": 260506
  },
  {
    "dataset": "Weather",
    "pred_len": 336,
    "variant": "NoDynFilt",
    "n": 3,
    "seeds": "2021,2022,2023",
    "mse_mean": 0.2829117178916931,
    "mse_std": 0.0006710177719654941,
    "mae_mean": 0.2981993754704793,
    "mae_std": 0.0007094061102321991,
    "mse_mean_trunc3": 0.282,
    "mse_std_trunc3": 0.0,
    "mae_mean_trunc3": 0.298,
    "mae_std_trunc3": 0.0,
    "duration_mean_seconds": 130.66666666666666,
    "peak_gpu_memory_max_mib": 417.101,
    "parameters_total": 260506
  },
  {
    "dataset": "Weather",
    "pred_len": 336,
    "variant": "NoSDE",
    "n": 3,
    "seeds": "2021,2022,2023",
    "mse_mean": 0.2829117178916931,
    "mse_std": 0.0006710177719654941,
    "mae_mean": 0.2981993754704793,
    "mae_std": 0.0007094061102321991,
    "mse_mean_trunc3": 0.282,
    "mse_std_trunc3": 0.0,
    "mae_mean_trunc3": 0.298,
    "mae_std_trunc3": 0.0,
    "duration_mean_seconds": 125.33333333333333,
    "peak_gpu_memory_max_mib": 415.39,
    "parameters_total": 260506
  },
  {
    "dataset": "Weather",
    "pred_len": 336,
    "variant": "WrongPhase",
    "n": 1,
    "seeds": "2021",
    "mse_mean": 0.26314234733581543,
    "mse_std": 0.0,
    "mae_mean": 0.28783118724823,
    "mae_std": 0.0,
    "mse_mean_trunc3": 0.263,
    "mse_std_trunc3": 0.0,
    "mae_mean_trunc3": 0.287,
    "mae_std_trunc3": 0.0,
    "duration_mean_seconds": 124.0,
    "peak_gpu_memory_max_mib": 423.421,
    "parameters_total": 137026
  },
  {
    "dataset": "Weather",
    "pred_len": 720,
    "variant": "DynamicOnly",
    "n": 1,
    "seeds": "2021",
    "mse_mean": 0.3579738438129425,
    "mse_std": 0.0,
    "mae_mean": 0.3477906584739685,
    "mae_std": 0.0,
    "mse_mean_trunc3": 0.357,
    "mse_std_trunc3": 0.0,
    "mae_mean_trunc3": 0.347,
    "mae_std_trunc3": 0.0,
    "duration_mean_seconds": 290.0,
    "peak_gpu_memory_max_mib": 779.335,
    "parameters_total": 359194
  },
  {
    "dataset": "Weather",
    "pred_len": 720,
    "variant": "FixedGate",
    "n": 1,
    "seeds": "2021",
    "mse_mean": 0.3406519889831543,
    "mse_std": 0.0,
    "mae_mean": 0.3393484055995941,
    "mae_std": 0.0,
    "mse_mean_trunc3": 0.34,
    "mse_std_trunc3": 0.0,
    "mae_mean_trunc3": 0.339,
    "mae_std_trunc3": 0.0,
    "duration_mean_seconds": 233.0,
    "peak_gpu_memory_max_mib": 781.982,
    "parameters_total": 359194
  },
  {
    "dataset": "Weather",
    "pred_len": 720,
    "variant": "Full",
    "n": 3,
    "seeds": "2021,2022,2023",
    "mse_mean": 0.34071064988772076,
    "mse_std": 0.0009184409981336792,
    "mae_mean": 0.3395013709863027,
    "mae_std": 0.0006311746158741369,
    "mse_mean_trunc3": 0.34,
    "mse_std_trunc3": 0.0,
    "mae_mean_trunc3": 0.339,
    "mae_std_trunc3": 0.0,
    "duration_mean_seconds": 235.33333333333334,
    "peak_gpu_memory_max_mib": 781.984,
    "parameters_total": 359194
  },
  {
    "dataset": "Weather",
    "pred_len": 720,
    "variant": "GlobalOnly",
    "n": 1,
    "seeds": "2021",
    "mse_mean": 0.3426583409309387,
    "mse_std": 0.0,
    "mae_mean": 0.3411775231361389,
    "mae_std": 0.0,
    "mse_mean_trunc3": 0.342,
    "mse_std_trunc3": 0.0,
    "mae_mean_trunc3": 0.341,
    "mae_std_trunc3": 0.0,
    "duration_mean_seconds": 323.0,
    "peak_gpu_memory_max_mib": 780.22,
    "parameters_total": 359194
  },
  {
    "dataset": "Weather",
    "pred_len": 720,
    "variant": "NoDynFilt",
    "n": 3,
    "seeds": "2021,2022,2023",
    "mse_mean": 0.35833948850631714,
    "mse_std": 0.0002625784195908296,
    "mae_mean": 0.3480043411254883,
    "mae_std": 0.00044236945400832813,
    "mse_mean_trunc3": 0.358,
    "mse_std_trunc3": 0.0,
    "mae_mean_trunc3": 0.348,
    "mae_std_trunc3": 0.0,
    "duration_mean_seconds": 260.6666666666667,
    "peak_gpu_memory_max_mib": 773.919,
    "parameters_total": 359194
  },
  {
    "dataset": "Weather",
    "pred_len": 720,
    "variant": "NoSDE",
    "n": 3,
    "seeds": "2021,2022,2023",
    "mse_mean": 0.35833948850631714,
    "mse_std": 0.0002625784195908296,
    "mae_mean": 0.3480043411254883,
    "mae_std": 0.00044236945400832813,
    "mse_mean_trunc3": 0.358,
    "mse_std_trunc3": 0.0,
    "mae_mean_trunc3": 0.348,
    "mae_std_trunc3": 0.0,
    "duration_mean_seconds": 256.6666666666667,
    "peak_gpu_memory_max_mib": 771.294,
    "parameters_total": 359194
  },
  {
    "dataset": "Weather",
    "pred_len": 720,
    "variant": "WrongPhase",
    "n": 1,
    "seeds": "2021",
    "mse_mean": 0.3427530825138092,
    "mse_std": 0.0,
    "mae_mean": 0.3412022888660431,
    "mae_std": 0.0,
    "mse_mean_trunc3": 0.342,
    "mse_std_trunc3": 0.0,
    "mae_mean_trunc3": 0.341,
    "mae_std_trunc3": 0.0,
    "duration_mean_seconds": 289.0,
    "peak_gpu_memory_max_mib": 780.099,
    "parameters_total": 235714
  }
]